ashclip/__init__.py
ashclip/main.py
ashclip-1.0.0.dist-info/METADATA
ashclip-1.0.0.dist-info/WHEEL
ashclip-1.0.0.dist-info/entry_points.txt
ashclip-1.0.0.dist-info/top_level.txt
ashclip-1.0.0.dist-info/RECORD
