Metadata-Version: 2.4
Name: ashclip
Version: 1.0.0
Summary: A discreet CLI tool to fetch file content from Nexus Hub to the clipboard via a hotkey.
Author: Heisenberg
Author-email: heisenberg@example.com
Classifier: Programming Language :: Python :: 3
Classifier: License :: OSI Approved :: MIT License
Classifier: Operating System :: OS Independent
Requires-Python: >=3.6
Requires-Dist: keyboard
Requires-Dist: pyperclip
Requires-Dist: requests
Dynamic: author
Dynamic: author-email
Dynamic: classifier
Dynamic: description-content-type
Dynamic: requires-dist
Dynamic: requires-python
Dynamic: summary
